mtsm-0.0.101.data/scripts/mtsm.py
tests/__init__.py
tests/base_class.py
tests/test_cache_system.py
tests/test_cdn.py
tests/test_connection_pool.py
tests/test_custom_content_injection.py
tests/test_custom_response_text_rewrite.py
tests/test_default_mirror.py
tests/test_developer_functions.py
tests/test_exception.py
tests/test_functions.py
tests/test_httpbin.py
tests/test_non_standard_port.py
tests/test_redirection.py
tests/test_regex.py
tests/test_verification.py
tests/utils.py
zmirror/CONSTS.py
zmirror/__init__.py
zmirror/cache_system.py
zmirror/config.py
zmirror/config_default.py
zmirror/connection_pool.py
zmirror/lru_dict.py
zmirror/threadlocal.py
zmirror/utils.py
zmirror/zmirror.py
zmirror/external_pkgs/__init__.py
zmirror/external_pkgs/ColorfulPyPrint/_Beep.py
zmirror/external_pkgs/ColorfulPyPrint/_ColorfulPrint.py
zmirror/external_pkgs/ColorfulPyPrint/__init__.py
zmirror/external_pkgs/ColorfulPyPrint/_logtime.py
zmirror/external_pkgs/ColorfulPyPrint/extra_output_destination/__init__.py
zmirror/external_pkgs/ColorfulPyPrint/thirdparty/__init__.py
zmirror/external_pkgs/ColorfulPyPrint/thirdparty/colorama/__init__.py
zmirror/external_pkgs/ColorfulPyPrint/thirdparty/colorama/ansi.py
zmirror/external_pkgs/ColorfulPyPrint/thirdparty/colorama/ansitowin32.py
zmirror/external_pkgs/ColorfulPyPrint/thirdparty/colorama/initialise.py
zmirror/external_pkgs/ColorfulPyPrint/thirdparty/colorama/win32.py
zmirror/external_pkgs/ColorfulPyPrint/thirdparty/colorama/winterm.py
mtsm-0.0.101.dist-info/METADATA
mtsm-0.0.101.dist-info/WHEEL
mtsm-0.0.101.dist-info/entry_points.txt
mtsm-0.0.101.dist-info/top_level.txt
mtsm-0.0.101.dist-info/RECORD
