Metadata-Version: 2.1
Name: mtsm
Version: 0.0.101
Summary: The funniest joke in the world
Home-page: http://github.com/storborg/funniest
Author: Flying Circus
Author-email: flyingcircus@example.com
License: MIT
Keywords: funniest joke comedy flying circus
Classifier: Development Status :: 3 - Alpha
Classifier: License :: OSI Approved :: MIT License
Classifier: Programming Language :: Python :: 2.7
Classifier: Topic :: Text Processing :: Linguistic
Requires-Dist: requests
Requires-Dist: flask (>=0.11)
Requires-Dist: cchardet (>=1.0)
Requires-Dist: fastcache (>=1.0.2)
Requires-Dist: codeclimate-test-reporter
Requires-Dist: lru-dict (>=1.1.5)
